odoo/addons/mail_template_attachment_i18n/README.rst
odoo/addons/mail_template_attachment_i18n/__init__.py
odoo/addons/mail_template_attachment_i18n/__manifest__.py
odoo/addons/mail_template_attachment_i18n/i18n/mail_template_attachment_i18n.pot
odoo/addons/mail_template_attachment_i18n/models/__init__.py
odoo/addons/mail_template_attachment_i18n/models/ir_attachment_language.py
odoo/addons/mail_template_attachment_i18n/models/mail_template.py
odoo/addons/mail_template_attachment_i18n/readme/CONFIGURE.rst
odoo/addons/mail_template_attachment_i18n/readme/CONTRIBUTORS.rst
odoo/addons/mail_template_attachment_i18n/readme/DESCRIPTION.rst
odoo/addons/mail_template_attachment_i18n/readme/USAGE.rst
odoo/addons/mail_template_attachment_i18n/security/ir.model.access.csv
odoo/addons/mail_template_attachment_i18n/static/description/icon.png
odoo/addons/mail_template_attachment_i18n/static/description/index.html
odoo/addons/mail_template_attachment_i18n/views/mail_template_view.xml
odoo11_addon_mail_template_attachment_i18n-11.0.1.0.0.99.dev7.dist-info/METADATA
odoo11_addon_mail_template_attachment_i18n-11.0.1.0.0.99.dev7.dist-info/WHEEL
odoo11_addon_mail_template_attachment_i18n-11.0.1.0.0.99.dev7.dist-info/top_level.txt
odoo11_addon_mail_template_attachment_i18n-11.0.1.0.0.99.dev7.dist-info/RECORD
